[
  {
    "id": "JFK",
    "name": "New York",
    "region": "na",
    "lat": 40.64,
    "lon": -73.78,
    "pop": 10,
    "biz": 10,
    "tour": 8,
    "slotPool": 36
  },
  {
    "id": "ORD",
    "name": "Chicago",
    "region": "na",
    "lat": 41.97,
    "lon": -87.9,
    "pop": 8,
    "biz": 8,
    "tour": 5,
    "slotPool": 28
  },
  {
    "id": "LAX",
    "name": "Los Angeles",
    "region": "na",
    "lat": 33.94,
    "lon": -118.41,
    "pop": 9,
    "biz": 8,
    "tour": 8,
    "slotPool": 30
  },
  {
    "id": "SFO",
    "name": "San Francisco",
    "region": "na",
    "lat": 37.62,
    "lon": -122.38,
    "pop": 6,
    "biz": 7,
    "tour": 7,
    "slotPool": 24
  },
  {
    "id": "MIA",
    "name": "Miami",
    "region": "na",
    "lat": 25.79,
    "lon": -80.29,
    "pop": 5,
    "biz": 5,
    "tour": 8,
    "slotPool": 22
  },
  {
    "id": "YYZ",
    "name": "Toronto",
    "region": "na",
    "lat": 43.68,
    "lon": -79.63,
    "pop": 6,
    "biz": 6,
    "tour": 5,
    "slotPool": 22
  },
  {
    "id": "MEX",
    "name": "Mexico City",
    "region": "na",
    "lat": 19.44,
    "lon": -99.07,
    "pop": 8,
    "biz": 5,
    "tour": 6,
    "slotPool": 22
  },
  {
    "id": "ATL",
    "name": "Atlanta",
    "region": "na",
    "lat": 33.64,
    "lon": -84.43,
    "pop": 6,
    "biz": 6,
    "tour": 4,
    "slotPool": 24
  },
  {
    "id": "DEN",
    "name": "Denver",
    "region": "na",
    "lat": 39.86,
    "lon": -104.67,
    "pop": 5,
    "biz": 5,
    "tour": 5,
    "slotPool": 20
  },
  {
    "id": "IAH",
    "name": "Houston",
    "region": "na",
    "lat": 29.98,
    "lon": -95.34,
    "pop": 5,
    "biz": 6,
    "tour": 3,
    "slotPool": 20
  },
  {
    "id": "SEA",
    "name": "Seattle",
    "region": "na",
    "lat": 47.45,
    "lon": -122.31,
    "pop": 5,
    "biz": 5,
    "tour": 4,
    "slotPool": 18
  },
  {
    "id": "BOS",
    "name": "Boston",
    "region": "na",
    "lat": 42.36,
    "lon": -71.01,
    "pop": 5,
    "biz": 6,
    "tour": 5,
    "slotPool": 20
  },
  {
    "id": "YVR",
    "name": "Vancouver",
    "region": "na",
    "lat": 49.19,
    "lon": -123.18,
    "pop": 4,
    "biz": 4,
    "tour": 5,
    "slotPool": 16
  },
  {
    "id": "HAV",
    "name": "Havana",
    "region": "na",
    "lat": 22.99,
    "lon": -82.41,
    "pop": 4,
    "biz": 3,
    "tour": 6,
    "slotPool": 12
  },
  {
    "id": "PTY",
    "name": "Panama City",
    "region": "na",
    "lat": 9.07,
    "lon": -79.38,
    "pop": 3,
    "biz": 4,
    "tour": 4,
    "slotPool": 12
  },
  {
    "id": "GRU",
    "name": "Sao Paulo",
    "region": "sa",
    "lat": -23.44,
    "lon": -46.47,
    "pop": 8,
    "biz": 6,
    "tour": 5,
    "slotPool": 22
  },
  {
    "id": "GIG",
    "name": "Rio de Janeiro",
    "region": "sa",
    "lat": -22.81,
    "lon": -43.25,
    "pop": 6,
    "biz": 4,
    "tour": 8,
    "slotPool": 18
  },
  {
    "id": "EZE",
    "name": "Buenos Aires",
    "region": "sa",
    "lat": -34.82,
    "lon": -58.54,
    "pop": 7,
    "biz": 5,
    "tour": 6,
    "slotPool": 20
  },
  {
    "id": "BOG",
    "name": "Bogota",
    "region": "sa",
    "lat": 4.7,
    "lon": -74.14,
    "pop": 5,
    "biz": 4,
    "tour": 4,
    "slotPool": 16
  },
  {
    "id": "LIM",
    "name": "Lima",
    "region": "sa",
    "lat": -12.02,
    "lon": -77.11,
    "pop": 5,
    "biz": 4,
    "tour": 5,
    "slotPool": 16
  },
  {
    "id": "SCL",
    "name": "Santiago",
    "region": "sa",
    "lat": -33.39,
    "lon": -70.79,
    "pop": 4,
    "biz": 4,
    "tour": 4,
    "slotPool": 14
  },
  {
    "id": "CCS",
    "name": "Caracas",
    "region": "sa",
    "lat": 10.6,
    "lon": -66.99,
    "pop": 4,
    "biz": 4,
    "tour": 3,
    "slotPool": 12
  },
  {
    "id": "LHR",
    "name": "London",
    "region": "eu",
    "lat": 51.47,
    "lon": -0.45,
    "pop": 9,
    "biz": 10,
    "tour": 9,
    "slotPool": 34
  },
  {
    "id": "CDG",
    "name": "Paris",
    "region": "eu",
    "lat": 49.01,
    "lon": 2.55,
    "pop": 8,
    "biz": 8,
    "tour": 10,
    "slotPool": 30
  },
  {
    "id": "FRA",
    "name": "Frankfurt",
    "region": "eu",
    "lat": 50.03,
    "lon": 8.57,
    "pop": 5,
    "biz": 9,
    "tour": 5,
    "slotPool": 28
  },
  {
    "id": "AMS",
    "name": "Amsterdam",
    "region": "eu",
    "lat": 52.31,
    "lon": 4.76,
    "pop": 4,
    "biz": 7,
    "tour": 7,
    "slotPool": 24
  },
  {
    "id": "MAD",
    "name": "Madrid",
    "region": "eu",
    "lat": 40.47,
    "lon": -3.57,
    "pop": 6,
    "biz": 6,
    "tour": 7,
    "slotPool": 22
  },
  {
    "id": "BCN",
    "name": "Barcelona",
    "region": "eu",
    "lat": 41.3,
    "lon": 2.08,
    "pop": 5,
    "biz": 5,
    "tour": 8,
    "slotPool": 18
  },
  {
    "id": "FCO",
    "name": "Rome",
    "region": "eu",
    "lat": 41.8,
    "lon": 12.25,
    "pop": 6,
    "biz": 5,
    "tour": 9,
    "slotPool": 22
  },
  {
    "id": "MXP",
    "name": "Milan",
    "region": "eu",
    "lat": 45.63,
    "lon": 8.72,
    "pop": 5,
    "biz": 7,
    "tour": 5,
    "slotPool": 20
  },
  {
    "id": "ZRH",
    "name": "Zurich",
    "region": "eu",
    "lat": 47.46,
    "lon": 8.55,
    "pop": 3,
    "biz": 7,
    "tour": 5,
    "slotPool": 18
  },
  {
    "id": "VIE",
    "name": "Vienna",
    "region": "eu",
    "lat": 48.11,
    "lon": 16.57,
    "pop": 4,
    "biz": 5,
    "tour": 6,
    "slotPool": 16
  },
  {
    "id": "MUC",
    "name": "Munich",
    "region": "eu",
    "lat": 48.35,
    "lon": 11.79,
    "pop": 4,
    "biz": 6,
    "tour": 5,
    "slotPool": 18
  },
  {
    "id": "TXL",
    "name": "Berlin",
    "region": "eu",
    "lat": 52.56,
    "lon": 13.29,
    "pop": 5,
    "biz": 5,
    "tour": 5,
    "slotPool": 18
  },
  {
    "id": "CPH",
    "name": "Copenhagen",
    "region": "eu",
    "lat": 55.62,
    "lon": 12.66,
    "pop": 4,
    "biz": 5,
    "tour": 5,
    "slotPool": 16
  },
  {
    "id": "ARN",
    "name": "Stockholm",
    "region": "eu",
    "lat": 59.65,
    "lon": 17.92,
    "pop": 4,
    "biz": 5,
    "tour": 4,
    "slotPool": 16
  },
  {
    "id": "DUB",
    "name": "Dublin",
    "region": "eu",
    "lat": 53.42,
    "lon": -6.27,
    "pop": 3,
    "biz": 4,
    "tour": 5,
    "slotPool": 14
  },
  {
    "id": "LIS",
    "name": "Lisbon",
    "region": "eu",
    "lat": 38.77,
    "lon": -9.13,
    "pop": 4,
    "biz": 4,
    "tour": 6,
    "slotPool": 14
  },
  {
    "id": "ATH",
    "name": "Athens",
    "region": "eu",
    "lat": 37.94,
    "lon": 23.94,
    "pop": 4,
    "biz": 4,
    "tour": 7,
    "slotPool": 14
  },
  {
    "id": "WAW",
    "name": "Warsaw",
    "region": "eu",
    "lat": 52.17,
    "lon": 20.97,
    "pop": 4,
    "biz": 3,
    "tour": 3,
    "slotPool": 12
  },
  {
    "id": "BUD",
    "name": "Budapest",
    "region": "eu",
    "lat": 47.44,
    "lon": 19.26,
    "pop": 3,
    "biz": 3,
    "tour": 5,
    "slotPool": 12
  },
  {
    "id": "SVO",
    "name": "Moscow",
    "region": "eu",
    "lat": 55.97,
    "lon": 37.41,
    "pop": 8,
    "biz": 6,
    "tour": 5,
    "slotPool": 20
  },
  {
    "id": "IST",
    "name": "Istanbul",
    "region": "eu",
    "lat": 40.98,
    "lon": 28.81,
    "pop": 7,
    "biz": 5,
    "tour": 7,
    "slotPool": 18
  },
  {
    "id": "CAI",
    "name": "Cairo",
    "region": "me",
    "lat": 30.12,
    "lon": 31.41,
    "pop": 7,
    "biz": 4,
    "tour": 7,
    "slotPool": 18
  },
  {
    "id": "DXB",
    "name": "Dubai",
    "region": "me",
    "lat": 25.25,
    "lon": 55.36,
    "pop": 4,
    "biz": 6,
    "tour": 5,
    "slotPool": 20
  },
  {
    "id": "TLV",
    "name": "Tel Aviv",
    "region": "me",
    "lat": 32.01,
    "lon": 34.89,
    "pop": 3,
    "biz": 4,
    "tour": 5,
    "slotPool": 12
  },
  {
    "id": "RUH",
    "name": "Riyadh",
    "region": "me",
    "lat": 24.96,
    "lon": 46.7,
    "pop": 4,
    "biz": 5,
    "tour": 2,
    "slotPool": 14
  },
  {
    "id": "DOH",
    "name": "Doha",
    "region": "me",
    "lat": 25.27,
    "lon": 51.61,
    "pop": 2,
    "biz": 4,
    "tour": 2,
    "slotPool": 12
  },
  {
    "id": "THR",
    "name": "Tehran",
    "region": "me",
    "lat": 35.69,
    "lon": 51.31,
    "pop": 6,
    "biz": 4,
    "tour": 3,
    "slotPool": 14
  },
  {
    "id": "JNB",
    "name": "Johannesburg",
    "region": "af",
    "lat": -26.14,
    "lon": 28.25,
    "pop": 5,
    "biz": 5,
    "tour": 5,
    "slotPool": 16
  },
  {
    "id": "LOS",
    "name": "Lagos",
    "region": "af",
    "lat": 6.58,
    "lon": 3.32,
    "pop": 6,
    "biz": 4,
    "tour": 3,
    "slotPool": 14
  },
  {
    "id": "NBO",
    "name": "Nairobi",
    "region": "af",
    "lat": -1.32,
    "lon": 36.93,
    "pop": 3,
    "biz": 3,
    "tour": 5,
    "slotPool": 12
  },
  {
    "id": "ADD",
    "name": "Addis Ababa",
    "region": "af",
    "lat": 8.98,
    "lon": 38.8,
    "pop": 3,
    "biz": 2,
    "tour": 3,
    "slotPool": 10
  },
  {
    "id": "ACC",
    "name": "Accra",
    "region": "af",
    "lat": 5.61,
    "lon": -0.17,
    "pop": 3,
    "biz": 3,
    "tour": 3,
    "slotPool": 10
  },
  {
    "id": "CMN",
    "name": "Casablanca",
    "region": "af",
    "lat": 33.37,
    "lon": -7.59,
    "pop": 3,
    "biz": 3,
    "tour": 4,
    "slotPool": 12
  },
  {
    "id": "HND",
    "name": "Tokyo",
    "region": "as",
    "lat": 35.55,
    "lon": 139.78,
    "pop": 10,
    "biz": 9,
    "tour": 7,
    "slotPool": 32
  },
  {
    "id": "KIX",
    "name": "Osaka",
    "region": "as",
    "lat": 34.79,
    "lon": 135.44,
    "pop": 7,
    "biz": 6,
    "tour": 5,
    "slotPool": 22
  },
  {
    "id": "SEL",
    "name": "Seoul",
    "region": "as",
    "lat": 37.47,
    "lon": 126.45,
    "pop": 7,
    "biz": 6,
    "tour": 5,
    "slotPool": 22
  },
  {
    "id": "PEK",
    "name": "Beijing",
    "region": "as",
    "lat": 40.08,
    "lon": 116.58,
    "pop": 9,
    "biz": 5,
    "tour": 6,
    "slotPool": 22
  },
  {
    "id": "SHA",
    "name": "Shanghai",
    "region": "as",
    "lat": 31.2,
    "lon": 121.34,
    "pop": 8,
    "biz": 6,
    "tour": 5,
    "slotPool": 22
  },
  {
    "id": "CAN",
    "name": "Guangzhou",
    "region": "as",
    "lat": 23.39,
    "lon": 113.31,
    "pop": 6,
    "biz": 4,
    "tour": 3,
    "slotPool": 16
  },
  {
    "id": "HKG",
    "name": "Hong Kong",
    "region": "as",
    "lat": 22.31,
    "lon": 113.91,
    "pop": 6,
    "biz": 8,
    "tour": 7,
    "slotPool": 24
  },
  {
    "id": "TPE",
    "name": "Taipei",
    "region": "as",
    "lat": 25.08,
    "lon": 121.23,
    "pop": 5,
    "biz": 5,
    "tour": 4,
    "slotPool": 18
  },
  {
    "id": "MNL",
    "name": "Manila",
    "region": "as",
    "lat": 14.51,
    "lon": 121.02,
    "pop": 5,
    "biz": 4,
    "tour": 4,
    "slotPool": 16
  },
  {
    "id": "BKK",
    "name": "Bangkok",
    "region": "as",
    "lat": 13.69,
    "lon": 100.75,
    "pop": 6,
    "biz": 5,
    "tour": 8,
    "slotPool": 20
  },
  {
    "id": "SGN",
    "name": "Saigon",
    "region": "as",
    "lat": 10.82,
    "lon": 106.66,
    "pop": 5,
    "biz": 3,
    "tour": 3,
    "slotPool": 12
  },
  {
    "id": "KUL",
    "name": "Kuala Lumpur",
    "region": "as",
    "lat": 2.75,
    "lon": 101.71,
    "pop": 4,
    "biz": 4,
    "tour": 4,
    "slotPool": 14
  },
  {
    "id": "SIN",
    "name": "Singapore",
    "region": "as",
    "lat": 1.36,
    "lon": 103.99,
    "pop": 5,
    "biz": 8,
    "tour": 6,
    "slotPool": 22
  },
  {
    "id": "CGK",
    "name": "Jakarta",
    "region": "as",
    "lat": -6.13,
    "lon": 106.66,
    "pop": 7,
    "biz": 4,
    "tour": 4,
    "slotPool": 16
  },
  {
    "id": "DEL",
    "name": "Delhi",
    "region": "as",
    "lat": 28.57,
    "lon": 77.1,
    "pop": 8,
    "biz": 5,
    "tour": 6,
    "slotPool": 18
  },
  {
    "id": "BOM",
    "name": "Mumbai",
    "region": "as",
    "lat": 19.09,
    "lon": 72.87,
    "pop": 8,
    "biz": 6,
    "tour": 5,
    "slotPool": 18
  },
  {
    "id": "MAA",
    "name": "Madras",
    "region": "as",
    "lat": 12.99,
    "lon": 80.17,
    "pop": 5,
    "biz": 3,
    "tour": 3,
    "slotPool": 12
  },
  {
    "id": "CCU",
    "name": "Calcutta",
    "region": "as",
    "lat": 22.65,
    "lon": 88.45,
    "pop": 6,
    "biz": 3,
    "tour": 3,
    "slotPool": 12
  },
  {
    "id": "KHI",
    "name": "Karachi",
    "region": "as",
    "lat": 24.91,
    "lon": 67.16,
    "pop": 5,
    "biz": 3,
    "tour": 2,
    "slotPool": 12
  },
  {
    "id": "DAC",
    "name": "Dacca",
    "region": "as",
    "lat": 23.84,
    "lon": 90.4,
    "pop": 5,
    "biz": 2,
    "tour": 2,
    "slotPool": 10
  },
  {
    "id": "SYD",
    "name": "Sydney",
    "region": "oc",
    "lat": -33.95,
    "lon": 151.18,
    "pop": 6,
    "biz": 6,
    "tour": 7,
    "slotPool": 20
  },
  {
    "id": "MEL",
    "name": "Melbourne",
    "region": "oc",
    "lat": -37.67,
    "lon": 144.84,
    "pop": 5,
    "biz": 5,
    "tour": 5,
    "slotPool": 18
  },
  {
    "id": "BNE",
    "name": "Brisbane",
    "region": "oc",
    "lat": -27.39,
    "lon": 153.12,
    "pop": 3,
    "biz": 3,
    "tour": 4,
    "slotPool": 12
  },
  {
    "id": "PER",
    "name": "Perth",
    "region": "oc",
    "lat": -31.94,
    "lon": 115.97,
    "pop": 3,
    "biz": 3,
    "tour": 3,
    "slotPool": 10
  },
  {
    "id": "AKL",
    "name": "Auckland",
    "region": "oc",
    "lat": -37.01,
    "lon": 174.79,
    "pop": 3,
    "biz": 3,
    "tour": 4,
    "slotPool": 12
  },
  {
    "id": "HNL",
    "name": "Honolulu",
    "region": "oc",
    "lat": 21.32,
    "lon": -157.92,
    "pop": 3,
    "biz": 3,
    "tour": 9,
    "slotPool": 14
  },
  {
    "id": "PHL",
    "name": "Philadelphia",
    "region": "na",
    "lat": 39.87,
    "lon": -75.24,
    "pop": 5,
    "biz": 5,
    "tour": 4,
    "slotPool": 18
  },
  {
    "id": "DCA",
    "name": "Washington",
    "region": "na",
    "lat": 38.85,
    "lon": -77.04,
    "pop": 5,
    "biz": 7,
    "tour": 6,
    "slotPool": 20
  },
  {
    "id": "DTW",
    "name": "Detroit",
    "region": "na",
    "lat": 42.21,
    "lon": -83.35,
    "pop": 5,
    "biz": 5,
    "tour": 2,
    "slotPool": 16
  },
  {
    "id": "MSP",
    "name": "Minneapolis",
    "region": "na",
    "lat": 44.88,
    "lon": -93.22,
    "pop": 4,
    "biz": 5,
    "tour": 3,
    "slotPool": 16
  },
  {
    "id": "STL",
    "name": "St. Louis",
    "region": "na",
    "lat": 38.75,
    "lon": -90.37,
    "pop": 4,
    "biz": 4,
    "tour": 3,
    "slotPool": 14
  },
  {
    "id": "MCO",
    "name": "Orlando",
    "region": "na",
    "lat": 28.43,
    "lon": -81.31,
    "pop": 3,
    "biz": 3,
    "tour": 8,
    "slotPool": 16
  },
  {
    "id": "LAS",
    "name": "Las Vegas",
    "region": "na",
    "lat": 36.08,
    "lon": -115.15,
    "pop": 3,
    "biz": 3,
    "tour": 8,
    "slotPool": 16
  },
  {
    "id": "PHX",
    "name": "Phoenix",
    "region": "na",
    "lat": 33.43,
    "lon": -112.01,
    "pop": 4,
    "biz": 4,
    "tour": 4,
    "slotPool": 14
  },
  {
    "id": "SAN",
    "name": "San Diego",
    "region": "na",
    "lat": 32.73,
    "lon": -117.19,
    "pop": 4,
    "biz": 3,
    "tour": 5,
    "slotPool": 14
  },
  {
    "id": "SLC",
    "name": "Salt Lake City",
    "region": "na",
    "lat": 40.79,
    "lon": -111.98,
    "pop": 3,
    "biz": 3,
    "tour": 3,
    "slotPool": 12
  },
  {
    "id": "YUL",
    "name": "Montreal",
    "region": "na",
    "lat": 45.47,
    "lon": -73.74,
    "pop": 5,
    "biz": 5,
    "tour": 5,
    "slotPool": 18
  },
  {
    "id": "YYC",
    "name": "Calgary",
    "region": "na",
    "lat": 51.11,
    "lon": -114.02,
    "pop": 3,
    "biz": 3,
    "tour": 3,
    "slotPool": 12
  },
  {
    "id": "CUN",
    "name": "Cancun",
    "region": "na",
    "lat": 21.04,
    "lon": -86.87,
    "pop": 2,
    "biz": 2,
    "tour": 8,
    "slotPool": 12
  },
  {
    "id": "GDL",
    "name": "Guadalajara",
    "region": "na",
    "lat": 20.52,
    "lon": -103.31,
    "pop": 4,
    "biz": 3,
    "tour": 3,
    "slotPool": 12
  },
  {
    "id": "MTY",
    "name": "Monterrey",
    "region": "na",
    "lat": 25.78,
    "lon": -100.11,
    "pop": 4,
    "biz": 4,
    "tour": 2,
    "slotPool": 12
  },
  {
    "id": "SJU",
    "name": "San Juan",
    "region": "na",
    "lat": 18.44,
    "lon": -66.0,
    "pop": 3,
    "biz": 3,
    "tour": 6,
    "slotPool": 12
  },
  {
    "id": "MDE",
    "name": "Medellin",
    "region": "sa",
    "lat": 6.16,
    "lon": -75.42,
    "pop": 4,
    "biz": 3,
    "tour": 3,
    "slotPool": 10
  },
  {
    "id": "UIO",
    "name": "Quito",
    "region": "sa",
    "lat": -0.14,
    "lon": -78.49,
    "pop": 3,
    "biz": 2,
    "tour": 4,
    "slotPool": 10
  },
  {
    "id": "ASU",
    "name": "Asuncion",
    "region": "sa",
    "lat": -25.24,
    "lon": -57.52,
    "pop": 2,
    "biz": 2,
    "tour": 2,
    "slotPool": 8
  },
  {
    "id": "MVD",
    "name": "Montevideo",
    "region": "sa",
    "lat": -34.84,
    "lon": -56.03,
    "pop": 3,
    "biz": 3,
    "tour": 3,
    "slotPool": 10
  },
  {
    "id": "BSB",
    "name": "Brasilia",
    "region": "sa",
    "lat": -15.87,
    "lon": -47.92,
    "pop": 4,
    "biz": 4,
    "tour": 2,
    "slotPool": 12
  },
  {
    "id": "REC",
    "name": "Recife",
    "region": "sa",
    "lat": -8.13,
    "lon": -34.92,
    "pop": 3,
    "biz": 2,
    "tour": 4,
    "slotPool": 10
  },
  {
    "id": "SSA",
    "name": "Salvador",
    "region": "sa",
    "lat": -12.91,
    "lon": -38.33,
    "pop": 3,
    "biz": 2,
    "tour": 5,
    "slotPool": 10
  },
  {
    "id": "FOR",
    "name": "Fortaleza",
    "region": "sa",
    "lat": -3.78,
    "lon": -38.53,
    "pop": 3,
    "biz": 2,
    "tour": 4,
    "slotPool": 10
  },
  {
    "id": "BRU",
    "name": "Brussels",
    "region": "eu",
    "lat": 50.9,
    "lon": 4.48,
    "pop": 4,
    "biz": 6,
    "tour": 5,
    "slotPool": 16
  },
  {
    "id": "GVA",
    "name": "Geneva",
    "region": "eu",
    "lat": 46.24,
    "lon": 6.11,
    "pop": 2,
    "biz": 6,
    "tour": 5,
    "slotPool": 14
  },
  {
    "id": "NCE",
    "name": "Nice",
    "region": "eu",
    "lat": 43.66,
    "lon": 7.22,
    "pop": 2,
    "biz": 3,
    "tour": 7,
    "slotPool": 12
  },
  {
    "id": "MAN",
    "name": "Manchester",
    "region": "eu",
    "lat": 53.35,
    "lon": -2.28,
    "pop": 4,
    "biz": 4,
    "tour": 3,
    "slotPool": 14
  },
  {
    "id": "EDI",
    "name": "Edinburgh",
    "region": "eu",
    "lat": 55.95,
    "lon": -3.37,
    "pop": 3,
    "biz": 3,
    "tour": 5,
    "slotPool": 12
  },
  {
    "id": "HAM",
    "name": "Hamburg",
    "region": "eu",
    "lat": 53.63,
    "lon": 10.0,
    "pop": 4,
    "biz": 5,
    "tour": 3,
    "slotPool": 14
  },
  {
    "id": "DUS",
    "name": "Dusseldorf",
    "region": "eu",
    "lat": 51.29,
    "lon": 6.77,
    "pop": 4,
    "biz": 5,
    "tour": 3,
    "slotPool": 14
  },
  {
    "id": "STR",
    "name": "Stuttgart",
    "region": "eu",
    "lat": 48.69,
    "lon": 9.19,
    "pop": 3,
    "biz": 5,
    "tour": 3,
    "slotPool": 12
  },
  {
    "id": "GOT",
    "name": "Gothenburg",
    "region": "eu",
    "lat": 57.66,
    "lon": 12.28,
    "pop": 2,
    "biz": 3,
    "tour": 3,
    "slotPool": 10
  },
  {
    "id": "OSL",
    "name": "Oslo",
    "region": "eu",
    "lat": 60.19,
    "lon": 11.1,
    "pop": 3,
    "biz": 4,
    "tour": 4,
    "slotPool": 12
  },
  {
    "id": "HEL",
    "name": "Helsinki",
    "region": "eu",
    "lat": 60.32,
    "lon": 24.96,
    "pop": 3,
    "biz": 4,
    "tour": 4,
    "slotPool": 12
  },
  {
    "id": "KRK",
    "name": "Krakow",
    "region": "eu",
    "lat": 50.08,
    "lon": 19.78,
    "pop": 3,
    "biz": 2,
    "tour": 5,
    "slotPool": 10
  },
  {
    "id": "BEG",
    "name": "Belgrade",
    "region": "eu",
    "lat": 44.82,
    "lon": 20.31,
    "pop": 3,
    "biz": 3,
    "tour": 3,
    "slotPool": 10
  },
  {
    "id": "ZAG",
    "name": "Zagreb",
    "region": "eu",
    "lat": 45.74,
    "lon": 16.07,
    "pop": 2,
    "biz": 2,
    "tour": 4,
    "slotPool": 10
  },
  {
    "id": "SOF",
    "name": "Sofia",
    "region": "eu",
    "lat": 42.7,
    "lon": 23.4,
    "pop": 3,
    "biz": 2,
    "tour": 3,
    "slotPool": 10
  },
  {
    "id": "OTP",
    "name": "Bucharest",
    "region": "eu",
    "lat": 44.57,
    "lon": 26.1,
    "pop": 4,
    "biz": 3,
    "tour": 3,
    "slotPool": 10
  },
  {
    "id": "KBP",
    "name": "Kiev",
    "region": "eu",
    "lat": 50.34,
    "lon": 30.89,
    "pop": 5,
    "biz": 3,
    "tour": 3,
    "slotPool": 12
  },
  {
    "id": "LED",
    "name": "Leningrad",
    "region": "eu",
    "lat": 59.8,
    "lon": 30.27,
    "pop": 6,
    "biz": 4,
    "tour": 5,
    "slotPool": 14
  },
  {
    "id": "PRG",
    "name": "Prague",
    "region": "eu",
    "lat": 50.1,
    "lon": 14.26,
    "pop": 3,
    "biz": 3,
    "tour": 6,
    "slotPool": 12
  },
  {
    "id": "AMM",
    "name": "Amman",
    "region": "me",
    "lat": 31.72,
    "lon": 35.99,
    "pop": 3,
    "biz": 3,
    "tour": 4,
    "slotPool": 10
  },
  {
    "id": "BEY",
    "name": "Beirut",
    "region": "me",
    "lat": 33.82,
    "lon": 35.49,
    "pop": 3,
    "biz": 4,
    "tour": 5,
    "slotPool": 12
  },
  {
    "id": "BGW",
    "name": "Baghdad",
    "region": "me",
    "lat": 33.26,
    "lon": 44.23,
    "pop": 5,
    "biz": 3,
    "tour": 2,
    "slotPool": 12
  },
  {
    "id": "KWI",
    "name": "Kuwait City",
    "region": "me",
    "lat": 29.24,
    "lon": 47.97,
    "pop": 3,
    "biz": 4,
    "tour": 2,
    "slotPool": 12
  },
  {
    "id": "BAH",
    "name": "Bahrain",
    "region": "me",
    "lat": 26.27,
    "lon": 50.63,
    "pop": 2,
    "biz": 4,
    "tour": 2,
    "slotPool": 10
  },
  {
    "id": "MCT",
    "name": "Muscat",
    "region": "me",
    "lat": 23.59,
    "lon": 58.28,
    "pop": 2,
    "biz": 3,
    "tour": 3,
    "slotPool": 10
  },
  {
    "id": "ALG",
    "name": "Algiers",
    "region": "af",
    "lat": 36.69,
    "lon": 3.22,
    "pop": 4,
    "biz": 3,
    "tour": 3,
    "slotPool": 12
  },
  {
    "id": "TUN",
    "name": "Tunis",
    "region": "af",
    "lat": 36.85,
    "lon": 10.23,
    "pop": 3,
    "biz": 3,
    "tour": 4,
    "slotPool": 10
  },
  {
    "id": "TIP",
    "name": "Tripoli",
    "region": "af",
    "lat": 32.66,
    "lon": 13.16,
    "pop": 3,
    "biz": 3,
    "tour": 2,
    "slotPool": 10
  },
  {
    "id": "DKR",
    "name": "Dakar",
    "region": "af",
    "lat": 14.74,
    "lon": -17.49,
    "pop": 3,
    "biz": 3,
    "tour": 3,
    "slotPool": 10
  },
  {
    "id": "ABJ",
    "name": "Abidjan",
    "region": "af",
    "lat": 5.26,
    "lon": -3.93,
    "pop": 3,
    "biz": 3,
    "tour": 2,
    "slotPool": 10
  },
  {
    "id": "EBB",
    "name": "Entebbe",
    "region": "af",
    "lat": 0.04,
    "lon": 32.44,
    "pop": 2,
    "biz": 2,
    "tour": 3,
    "slotPool": 8
  },
  {
    "id": "DAR",
    "name": "Dar es Salaam",
    "region": "af",
    "lat": -6.88,
    "lon": 39.2,
    "pop": 3,
    "biz": 2,
    "tour": 3,
    "slotPool": 8
  },
  {
    "id": "HRE",
    "name": "Harare",
    "region": "af",
    "lat": -17.92,
    "lon": 31.09,
    "pop": 2,
    "biz": 2,
    "tour": 3,
    "slotPool": 8
  },
  {
    "id": "CPT",
    "name": "Cape Town",
    "region": "af",
    "lat": -33.97,
    "lon": 18.6,
    "pop": 4,
    "biz": 4,
    "tour": 6,
    "slotPool": 14
  },
  {
    "id": "LAD",
    "name": "Luanda",
    "region": "af",
    "lat": -8.85,
    "lon": 13.23,
    "pop": 3,
    "biz": 2,
    "tour": 2,
    "slotPool": 8
  },
  {
    "id": "PUS",
    "name": "Busan",
    "region": "as",
    "lat": 35.18,
    "lon": 128.94,
    "pop": 4,
    "biz": 3,
    "tour": 3,
    "slotPool": 12
  },
  {
    "id": "NGO",
    "name": "Nagoya",
    "region": "as",
    "lat": 35.25,
    "lon": 136.92,
    "pop": 5,
    "biz": 5,
    "tour": 3,
    "slotPool": 14
  },
  {
    "id": "FUK",
    "name": "Fukuoka",
    "region": "as",
    "lat": 33.59,
    "lon": 130.45,
    "pop": 4,
    "biz": 4,
    "tour": 3,
    "slotPool": 12
  },
  {
    "id": "CTS",
    "name": "Sapporo",
    "region": "as",
    "lat": 42.78,
    "lon": 141.68,
    "pop": 3,
    "biz": 3,
    "tour": 4,
    "slotPool": 12
  },
  {
    "id": "CTU",
    "name": "Chengdu",
    "region": "as",
    "lat": 30.58,
    "lon": 103.95,
    "pop": 5,
    "biz": 3,
    "tour": 3,
    "slotPool": 12
  },
  {
    "id": "XIY",
    "name": "Xian",
    "region": "as",
    "lat": 34.44,
    "lon": 108.75,
    "pop": 4,
    "biz": 2,
    "tour": 4,
    "slotPool": 10
  },
  {
    "id": "WUH",
    "name": "Wuhan",
    "region": "as",
    "lat": 30.78,
    "lon": 114.21,
    "pop": 5,
    "biz": 3,
    "tour": 2,
    "slotPool": 10
  },
  {
    "id": "SHE",
    "name": "Shenyang",
    "region": "as",
    "lat": 41.64,
    "lon": 123.49,
    "pop": 4,
    "biz": 3,
    "tour": 2,
    "slotPool": 10
  },
  {
    "id": "KMG",
    "name": "Kunming",
    "region": "as",
    "lat": 24.99,
    "lon": 102.74,
    "pop": 3,
    "biz": 2,
    "tour": 3,
    "slotPool": 8
  },
  {
    "id": "HAN",
    "name": "Hanoi",
    "region": "as",
    "lat": 21.21,
    "lon": 105.8,
    "pop": 4,
    "biz": 2,
    "tour": 3,
    "slotPool": 10
  },
  {
    "id": "PNH",
    "name": "Phnom Penh",
    "region": "as",
    "lat": 11.55,
    "lon": 104.84,
    "pop": 2,
    "biz": 2,
    "tour": 3,
    "slotPool": 8
  },
  {
    "id": "RGN",
    "name": "Rangoon",
    "region": "as",
    "lat": 16.91,
    "lon": 96.13,
    "pop": 3,
    "biz": 2,
    "tour": 3,
    "slotPool": 8
  },
  {
    "id": "DPS",
    "name": "Bali",
    "region": "as",
    "lat": -8.75,
    "lon": 115.17,
    "pop": 2,
    "biz": 2,
    "tour": 7,
    "slotPool": 10
  },
  {
    "id": "SUB",
    "name": "Surabaya",
    "region": "as",
    "lat": -7.38,
    "lon": 112.79,
    "pop": 4,
    "biz": 2,
    "tour": 2,
    "slotPool": 10
  },
  {
    "id": "CEB",
    "name": "Cebu",
    "region": "as",
    "lat": 10.31,
    "lon": 123.98,
    "pop": 3,
    "biz": 2,
    "tour": 4,
    "slotPool": 8
  },
  {
    "id": "HYD",
    "name": "Hyderabad",
    "region": "as",
    "lat": 17.45,
    "lon": 78.47,
    "pop": 5,
    "biz": 3,
    "tour": 3,
    "slotPool": 10
  },
  {
    "id": "BLR",
    "name": "Bangalore",
    "region": "as",
    "lat": 13.2,
    "lon": 77.71,
    "pop": 5,
    "biz": 4,
    "tour": 3,
    "slotPool": 10
  },
  {
    "id": "LHE",
    "name": "Lahore",
    "region": "as",
    "lat": 31.52,
    "lon": 74.4,
    "pop": 5,
    "biz": 2,
    "tour": 3,
    "slotPool": 10
  },
  {
    "id": "ADL",
    "name": "Adelaide",
    "region": "oc",
    "lat": -34.95,
    "lon": 138.53,
    "pop": 3,
    "biz": 3,
    "tour": 3,
    "slotPool": 10
  },
  {
    "id": "WLG",
    "name": "Wellington",
    "region": "oc",
    "lat": -41.33,
    "lon": 174.81,
    "pop": 2,
    "biz": 3,
    "tour": 3,
    "slotPool": 8
  },
  {
    "id": "CHC",
    "name": "Christchurch",
    "region": "oc",
    "lat": -43.49,
    "lon": 172.53,
    "pop": 2,
    "biz": 2,
    "tour": 4,
    "slotPool": 8
  },
  {
    "id": "NAN",
    "name": "Nadi",
    "region": "oc",
    "lat": -17.76,
    "lon": 177.44,
    "pop": 1,
    "biz": 1,
    "tour": 6,
    "slotPool": 8
  },
  {
    "id": "PPT",
    "name": "Papeete",
    "region": "oc",
    "lat": -17.56,
    "lon": -149.61,
    "pop": 1,
    "biz": 1,
    "tour": 6,
    "slotPool": 8
  },
  {
    "id": "GUM",
    "name": "Guam",
    "region": "oc",
    "lat": 13.48,
    "lon": 144.8,
    "pop": 1,
    "biz": 2,
    "tour": 4,
    "slotPool": 8
  }
]
